promptkit/__init__.py
promptkit/cli.py
promptkit/installer.py
promptkit/packs.py
promptkit_builtin_packs/__init__.py
promptkit_builtin_packs/__pycache__/__init__.cpython-313.pyc
promptkit_builtin_packs/execplan/agents_snippet.md
promptkit_builtin_packs/execplan/pack.json
promptkit_builtin_packs/execplan/files/PLANS.md
promptkitx-0.1.2.dist-info/licenses/LICENSE
promptkitx-0.1.2.dist-info/METADATA
promptkitx-0.1.2.dist-info/WHEEL
promptkitx-0.1.2.dist-info/entry_points.txt
promptkitx-0.1.2.dist-info/top_level.txt
promptkitx-0.1.2.dist-info/RECORD
