Metadata-Version: 2.4
Name: promptkitx
Version: 0.1.2
Summary: Prompt pack manager to install AGENTS snippets and .agent templates (ExecPlan and more)
Author-email: Mike Wong <mikewong23571@users.noreply.github.com>
License-Expression: MIT
Project-URL: Homepage, https://github.com/mikewong23571/promptkit
Project-URL: Bug Tracker, https://github.com/mikewong23571/promptkit/issues
Project-URL: Source Code, https://github.com/mikewong23571/promptkit
Keywords: codex,execplan,planning,agents,prompt,cli
Classifier: Programming Language :: Python :: 3
Classifier: Programming Language :: Python :: 3.9
Classifier: Programming Language :: Python :: 3.10
Classifier: Programming Language :: Python :: 3.11
Classifier: Programming Language :: Python :: 3.12
Classifier: Programming Language :: Python :: 3.13
Classifier: Intended Audience :: Developers
Classifier: Operating System :: OS Independent
Requires-Python: >=3.9
License-File: LICENSE
Provides-Extra: dev
Requires-Dist: ruff>=0.6; extra == "dev"
Requires-Dist: black>=24.10; extra == "dev"
Requires-Dist: mypy>=1.13; extra == "dev"
Dynamic: license-file
